catflow/__init__.py
catflow/analyzer/__init__.py
catflow/analyzer/atomic/__init__.py
catflow/analyzer/atomic/atomic_energy.py
catflow/analyzer/atomic/utils.py
catflow/analyzer/graph/__init__.py
catflow/analyzer/graph/plotting.py
catflow/analyzer/metad/__init__.py
catflow/analyzer/metad/colvar.py
catflow/analyzer/metad/fes.py
catflow/analyzer/metad/hills.py
catflow/analyzer/metad/profile.py
catflow/analyzer/metad/string.py
catflow/analyzer/structure/__init__.py
catflow/analyzer/structure/cluster.py
catflow/analyzer/structure/coordination_number.py
catflow/analyzer/structure/dynamic_selection.py
catflow/analyzer/structure/lindemann_index.py
catflow/analyzer/tesla/__init__.py
catflow/analyzer/tesla/ai2_kit/__init__.py
catflow/analyzer/tesla/ai2_kit/exploration.py
catflow/analyzer/tesla/ai2_kit/labeling.py
catflow/analyzer/tesla/ai2_kit/task.py
catflow/analyzer/tesla/ai2_kit/training.py
catflow/analyzer/tesla/base/__init__.py
catflow/analyzer/tesla/base/exploration.py
catflow/analyzer/tesla/base/labeling.py
catflow/analyzer/tesla/base/task.py
catflow/analyzer/tesla/base/training.py
catflow/analyzer/tesla/dpgen/__init__.py
catflow/analyzer/tesla/dpgen/exploration.py
catflow/analyzer/tesla/dpgen/labeling.py
catflow/analyzer/tesla/dpgen/task.py
catflow/analyzer/tesla/dpgen/training.py
catflow/cmdline/__init__.py
catflow/cmdline/base.py
catflow/cmdline/calculation/__init__.py
catflow/cmdline/calculation/dpgen.py
catflow/cmdline/calculation/vasp.py
catflow/cmdline/workflow/__init__.py
catflow/cmdline/workflow/pmf.py
catflow/cmdline/workflow/tesla.py
catflow/tasker/__init__.py
catflow/tasker/__main__.py
catflow/tasker/calculation/__init__.py
catflow/tasker/calculation/cp2k.py
catflow/tasker/calculation/dpgen.py
catflow/tasker/calculation/vasp.py
catflow/tasker/code/__init__.py
catflow/tasker/code/base.py
catflow/tasker/code/vasp.py
catflow/tasker/configs/workflow/pmf_cp2k.yml
catflow/tasker/flows/__init__.py
catflow/tasker/flows/pmf_flow.py
catflow-0.5.1.dist-info/LICENSE
catflow-0.5.1.dist-info/METADATA
catflow-0.5.1.dist-info/WHEEL
catflow-0.5.1.dist-info/entry_points.txt
catflow-0.5.1.dist-info/RECORD
