Metadata-Version: 2.1
Name: catflow
Version: 0.5.1
Summary: Analyzing tool for deep learning based chemical research.
Home-page: https://github.com/chenggroup/CatFlow
License: Apache-2.0
Author: Cloudac7
Author-email: scottryuu@outlook.com
Requires-Python: >=3.9,<4.0
Classifier: License :: OSI Approved :: Apache Software License
Classifier: Programming Language :: Python :: 3
Classifier: Programming Language :: Python :: 3.9
Classifier: Programming Language :: Python :: 3.10
Classifier: Programming Language :: Python :: 3.11
Classifier: Programming Language :: Python :: 3.12
Requires-Dist: ai2-kit (>=0.9.0)
Requires-Dist: ase (>=3.21.1,<4.0.0)
Requires-Dist: click
Requires-Dist: dpdata
Requires-Dist: dpdispatcher (>=0.5.6,<0.6.0)
Requires-Dist: dpgen (>=0.11.1,<0.12.0)
Requires-Dist: dscribe (>=1.2.2,<2.0.0)
Requires-Dist: dynaconf
Requires-Dist: fire (>=0.5.0,<0.6.0)
Requires-Dist: h5py (>=3.10.0,<4.0.0)
Requires-Dist: matplotlib (>=3.7.1,<4.0.0)
Requires-Dist: mdanalysis (>=2.2,<3.0)
Requires-Dist: numpy (>=1.24,<2.0)
Requires-Dist: pandas (>=1.3.3,<2.0.0)
Requires-Dist: pymatgen (>=2023.5.10,<2024.0.0)
Requires-Dist: ruamel-yaml (>=0.17.21,<0.18.0)
Requires-Dist: scipy (>=1.10,<2.0)
Requires-Dist: seaborn (>=0.12.2,<0.13.0)
Project-URL: Repository, https://github.com/chenggroup/CatFlow
